meishiki/__init__.py
meishiki/consts.py
meishiki/consts.yaml
meishiki/errors.py
meishiki/meishiki.py
meishiki/output.py
meishiki/unsei.py
meishiki/util.py
meishiki-0.3.12.dist-info/licenses/LICENSE
meishiki-0.3.12.dist-info/METADATA
meishiki-0.3.12.dist-info/WHEEL
meishiki-0.3.12.dist-info/top_level.txt
meishiki-0.3.12.dist-info/RECORD
