Metadata-Version: 2.4
Name: meishiki
Version: 0.3.12
Summary: Calculation of Four Pillars of Destiny
Home-page: 
Author: tk42
Author-email: nsplat+pip@gmail.com
Requires-Python: >=3.7
License-File: LICENSE
Requires-Dist: jinja2>=2.11.2
Requires-Dist: pyyaml>=5.3.1
Requires-Dist: python-box>=5.2.0
Dynamic: author
Dynamic: author-email
Dynamic: description
Dynamic: description-content-type
Dynamic: license-file
Dynamic: requires-dist
Dynamic: requires-python
Dynamic: summary
